streamz/__init__.py
streamz/batch.py
streamz/collection.py
streamz/core.py
streamz/dask.py
streamz/graph.py
streamz/orderedweakset.py
streamz/plugins.py
streamz/river.py
streamz/sinks.py
streamz/sources.py
streamz/utils.py
streamz/utils_test.py
streamz/dataframe/__init__.py
streamz/dataframe/aggregations.py
streamz/dataframe/core.py
streamz/dataframe/utils.py
streamz/dataframe/tests/test_dataframe_utils.py
streamz/dataframe/tests/test_dataframes.py
streamz/tests/__init__.py
streamz/tests/py3_test_core.py
streamz/tests/test_batch.py
streamz/tests/test_core.py
streamz/tests/test_dask.py
streamz/tests/test_graph.py
streamz/tests/test_kafka.py
streamz/tests/test_plugins.py
streamz/tests/test_sinks.py
streamz/tests/test_sources.py
streamz-0.6.5.dist-info/licenses/LICENSE.txt
streamz-0.6.5.dist-info/METADATA
streamz-0.6.5.dist-info/WHEEL
streamz-0.6.5.dist-info/top_level.txt
streamz-0.6.5.dist-info/RECORD
