Metadata-Version: 2.4
Name: streamz
Version: 0.6.5
Summary: Streams
Home-page: http://github.com/python-streamz/streamz/
Maintainer: Matthew Rocklin
Maintainer-email: mrocklin@gmail.com
License: BSD
Keywords: streams
Requires-Python: >=3.9
License-File: LICENSE.txt
Requires-Dist: tornado
Requires-Dist: toolz
Requires-Dist: zict
Requires-Dist: setuptools
Dynamic: description
Dynamic: home-page
Dynamic: keywords
Dynamic: license
Dynamic: license-file
Dynamic: maintainer
Dynamic: maintainer-email
Dynamic: requires-dist
Dynamic: requires-python
Dynamic: summary
